{
    "entities": [
        {
            "id": "T3",
            "type": "Phenotype",
            "name": "elite",
            "WTO": "WTO:0000048"
        },
        {
            "id": "T4",
            "type": "Plant",
            "name": "wheat",
            "NCBI_Taxonomy": "4565"
        },
        {
            "id": "T5",
            "type": "Phenotype",
            "name": "elite wheat",
            "WTO": "WTO:0000048"
        },
        {
            "id": "T6",
            "type": "Phenotype",
            "name": "winter wheat",
            "WTO": "WTO:0000060"
        },
        {
            "id": "T7",
            "type": "Plant",
            "name": "wheat",
            "NCBI_Taxonomy": "4565"
        },
        {
            "id": "T8",
            "type": "Trait",
            "name": "wheat production",
            "WTO": "WTO:0000611"
        },
        {
            "id": "T9",
            "type": "Plant",
            "name": "wheat",
            "NCBI_Taxonomy": "4565"
        },
        {
            "id": "T10",
            "type": "Plant",
            "name": "wheat",
            "NCBI_Taxonomy": "4565"
        },
        {
            "id": "T11",
            "type": "Trait",
            "name": "flowering time",
            "WTO": "WTO:0000082"
        },
        {
            "id": "T12",
            "type": "Plant",
            "name": "wheat",
            "NCBI_Taxonomy": "4565"
        },
        {
            "id": "T13",
            "type": "Phenotype",
            "name": "elite wheat",
            "WTO": "WTO:0000048"
        },
        {
            "id": "T14",
            "type": "Plant",
            "name": "wheat",
            "NCBI_Taxonomy": "4565"
        },
        {
            "id": "T15",
            "type": "Trait",
            "name": "yield",
            "WTO": "WTO:0000071"
        },
        {
            "id": "T16",
            "type": "Trait",
            "name": "wheat production",
            "WTO": "WTO:0000611"
        },
        {
            "id": "T17",
            "type": "Plant",
            "name": "wheat",
            "NCBI_Taxonomy": "4565"
        }
    ],
    "equivalences": [],
    "relationships": []
}