{
    "entities": [
        {
            "id": "T51",
            "type": "Gene",
            "name": "plasminogen activators",
            "Name": "plasminogenactivators"
        },
        {
            "id": "T54",
            "type": "Gene",
            "name": "PA",
            "Name": "pa"
        },
        {
            "id": "T16",
            "type": "Gene",
            "name": "urokinase",
            "Name": "urokinase"
        },
        {
            "id": "T17",
            "type": "Gene",
            "name": "u-PA",
            "Name": "upa"
        },
        {
            "id": "T23",
            "type": "Gene",
            "name": "tissue plasminogen activator",
            "Name": "tissueplasminogenactivator"
        },
        {
            "id": "T28",
            "type": "Gene",
            "name": "t-PA",
            "Name": "tpa"
        },
        {
            "id": "T31",
            "type": "Gene",
            "name": "streptokinase",
            "Name": "streptokinase"
        },
        {
            "id": "T35",
            "type": "Gene",
            "name": "SK",
            "Name": "sk"
        },
        {
            "id": "T36",
            "type": "Gene",
            "name": "plasminogen-streptokinase-activator-complex",
            "Name": "plasminogenstreptokinaseactivatorcomplex"
        },
        {
            "id": "T41",
            "type": "Gene",
            "name": "PSAC",
            "Name": "psac"
        },
        {
            "id": "T42",
            "type": "Gene",
            "name": "t-PA",
            "Name": "tpa"
        },
        {
            "id": "T43",
            "type": "Gene",
            "name": "PA",
            "Name": "pa"
        },
        {
            "id": "T44",
            "type": "Gene",
            "name": "plasmin",
            "Name": "plasmin"
        },
        {
            "id": "T45",
            "type": "Gene",
            "name": "Pli",
            "Name": "pli"
        },
        {
            "id": "T46",
            "type": "Gene",
            "name": "PA",
            "Name": "pa"
        },
        {
            "id": "T47",
            "type": "Gene",
            "name": "t-PA",
            "Name": "tpa"
        },
        {
            "id": "T48",
            "type": "Gene",
            "name": "SK",
            "Name": "sk"
        },
        {
            "id": "T49",
            "type": "Gene",
            "name": "PSAC",
            "Name": "psac"
        },
        {
            "id": "T50",
            "type": "Gene",
            "name": "urokinase",
            "Name": "urokinase"
        },
        {
            "id": "T8",
            "type": "Chemical",
            "name": "singlet oxygen",
            "Name": "singletoxygen"
        },
        {
            "id": "T9",
            "type": "Chemical",
            "name": "1O2",
            "Name": "1o2"
        },
        {
            "id": "T10",
            "type": "Chemical",
            "name": "chloramine T",
            "Name": "chloraminet"
        },
        {
            "id": "T11",
            "type": "Chemical",
            "name": "CT",
            "Name": "ct"
        },
        {
            "id": "T52",
            "type": "Gene",
            "name": "plasmatic PAI-1",
            "Name": "plasmaticpai1"
        },
        {
            "id": "T53",
            "type": "Gene",
            "name": "plasmin",
            "Name": "plasmin"
        },
        {
            "id": "T12",
            "type": "Chemical",
            "name": "arginine",
            "Name": "arginine"
        },
        {
            "id": "T1",
            "type": "Chemical",
            "name": "CT",
            "Name": "ct"
        },
        {
            "id": "T13",
            "type": "Gene",
            "name": "plasmin",
            "Name": "plasmin"
        },
        {
            "id": "T2",
            "type": "Chemical",
            "name": "arginine",
            "Name": "arginine"
        },
        {
            "id": "T3",
            "type": "Chemical",
            "name": "CT",
            "Name": "ct"
        },
        {
            "id": "T4",
            "type": "Chemical",
            "name": "citrate",
            "Name": "citrate"
        },
        {
            "id": "T5",
            "type": "Chemical",
            "name": "EDTA",
            "Name": "edta"
        },
        {
            "id": "T14",
            "type": "Gene",
            "name": "PA",
            "Name": "pa"
        },
        {
            "id": "T15",
            "type": "Gene",
            "name": "Pli",
            "Name": "pli"
        },
        {
            "id": "T6",
            "type": "Chemical",
            "name": "arginine",
            "Name": "arginine"
        },
        {
            "id": "T7",
            "type": "Chemical",
            "name": "Val-Leu-Lys",
            "Name": "valleulys"
        },
        {
            "id": "T18",
            "type": "Gene",
            "name": "PA",
            "Name": "pa"
        },
        {
            "id": "T19",
            "type": "Gene",
            "name": "Pli",
            "Name": "pli"
        },
        {
            "id": "T20",
            "type": "Gene",
            "name": "Pli",
            "Name": "pli"
        },
        {
            "id": "T21",
            "type": "Gene",
            "name": "PA",
            "Name": "pa"
        },
        {
            "id": "T22",
            "type": "Gene",
            "name": "PA",
            "Name": "pa"
        },
        {
            "id": "T24",
            "type": "Gene",
            "name": "Pli",
            "Name": "pli"
        },
        {
            "id": "T25",
            "type": "Gene",
            "name": "Pli",
            "Name": "pli"
        },
        {
            "id": "T26",
            "type": "Gene",
            "name": "u-PA",
            "Name": "upa"
        },
        {
            "id": "T27",
            "type": "Gene",
            "name": "t-PA",
            "Name": "tpa"
        },
        {
            "id": "T29",
            "type": "Gene",
            "name": "PA",
            "Name": "pa"
        },
        {
            "id": "T30",
            "type": "Gene",
            "name": "u-PA",
            "Name": "upa"
        },
        {
            "id": "T32",
            "type": "Gene",
            "name": "t-PA",
            "Name": "tpa"
        },
        {
            "id": "T33",
            "type": "Gene",
            "name": "SK",
            "Name": "sk"
        },
        {
            "id": "T34",
            "type": "Gene",
            "name": "PSAC",
            "Name": "psac"
        },
        {
            "id": "T37",
            "type": "Gene",
            "name": "PAs",
            "Name": "pas"
        },
        {
            "id": "T38",
            "type": "Gene",
            "name": "plasmatic Pli",
            "Name": "plasmaticpli"
        },
        {
            "id": "T39",
            "type": "Gene",
            "name": "plasmin",
            "Name": "plasmin"
        },
        {
            "id": "T40",
            "type": "Gene",
            "name": "PA",
            "Name": "pa"
        }
    ],
    "equivalences": [],
    "relationships": [
        {
            "type": "Substrate",
            "source": "T2",
            "target": "T13"
        },
        {
            "type": "Substrate",
            "source": "T6",
            "target": "T15"
        },
        {
            "type": "Substrate",
            "source": "T6",
            "target": "T14"
        }
    ]
}