{
    "entities": [
        {
            "id": "T7",
            "type": "Chemical",
            "name": "betamethasone",
            "Name": "betamethasone"
        },
        {
            "id": "T8",
            "type": "Chemical",
            "name": "11beta hydroxysteroid",
            "Name": "11betahydroxysteroid"
        },
        {
            "id": "T28",
            "type": "Gene",
            "name": "11beta hydroxysteroid dehydrogenase types 1 and 2",
            "Name": "11betahydroxysteroiddehydrogenasetypes1and2"
        },
        {
            "id": "T27",
            "type": "Gene",
            "name": "glucocorticoid receptor",
            "Name": "glucocorticoidreceptor"
        },
        {
            "id": "T3",
            "type": "Chemical",
            "name": "betamethasone",
            "Name": "betamethasone"
        },
        {
            "id": "T4",
            "type": "Chemical",
            "name": "betamethasone",
            "Name": "betamethasone"
        },
        {
            "id": "T5",
            "type": "Chemical",
            "name": "11beta hydroxysteroid",
            "Name": "11betahydroxysteroid"
        },
        {
            "id": "T18",
            "type": "Gene",
            "name": "11beta hydroxysteroid dehydrogenase",
            "Name": "11betahydroxysteroiddehydrogenase"
        },
        {
            "id": "T19",
            "type": "Gene",
            "name": "11beta HSD",
            "Name": "11betahsd"
        },
        {
            "id": "T20",
            "type": "Gene",
            "name": "glucocorticoid receptor",
            "Name": "glucocorticoidreceptor"
        },
        {
            "id": "T21",
            "type": "Gene",
            "name": "GR",
            "Name": "gr"
        },
        {
            "id": "T6",
            "type": "Chemical",
            "name": "betamethasone",
            "Name": "betamethasone"
        },
        {
            "id": "T22",
            "type": "Gene",
            "name": "11beta HSD-1",
            "Name": "11betahsd1"
        },
        {
            "id": "T23",
            "type": "Gene",
            "name": "11beta HSD-2",
            "Name": "11betahsd2"
        },
        {
            "id": "T24",
            "type": "Gene",
            "name": "GRalpha",
            "Name": "gralpha"
        },
        {
            "id": "T25",
            "type": "Gene",
            "name": "11beta HSD-2",
            "Name": "11betahsd2"
        },
        {
            "id": "T26",
            "type": "Gene",
            "name": "11beta HSD",
            "Name": "11betahsd"
        },
        {
            "id": "T1",
            "type": "Chemical",
            "name": "betamethasone",
            "Name": "betamethasone"
        },
        {
            "id": "T9",
            "type": "Gene",
            "name": "11beta HSD-1",
            "Name": "11betahsd1"
        },
        {
            "id": "T2",
            "type": "Chemical",
            "name": "betamethasone",
            "Name": "betamethasone"
        },
        {
            "id": "T10",
            "type": "Gene",
            "name": "11beta HSD-2",
            "Name": "11betahsd2"
        },
        {
            "id": "T11",
            "type": "Gene",
            "name": "GRalpha",
            "Name": "gralpha"
        },
        {
            "id": "T12",
            "type": "Gene",
            "name": "11beta HSD-1",
            "Name": "11betahsd1"
        },
        {
            "id": "T13",
            "type": "Gene",
            "name": "interleukin (IL)-1beta",
            "Name": "interleukinil1beta"
        },
        {
            "id": "T14",
            "type": "Gene",
            "name": "tumor necrosis factor alpha",
            "Name": "tumornecrosisfactoralpha"
        },
        {
            "id": "T15",
            "type": "Gene",
            "name": "TNF-alpha",
            "Name": "tnfalpha"
        },
        {
            "id": "T16",
            "type": "Gene",
            "name": "11beta HSD-2",
            "Name": "11betahsd2"
        },
        {
            "id": "T17",
            "type": "Gene",
            "name": "11beta HSD",
            "Name": "11betahsd"
        }
    ],
    "equivalences": [],
    "relationships": [
        {
            "type": "Indirect downregulator",
            "source": "T2",
            "target": "T10"
        },
        {
            "type": "Inhibitor",
            "source": "T2",
            "target": "T10"
        }
    ]
}