{
    "entities": [
        {
            "id": "T14",
            "type": "Gene",
            "name": "P450scc",
            "Name": "p450scc"
        },
        {
            "id": "T15",
            "type": "Gene",
            "name": "CYP17",
            "Name": "cyp17"
        },
        {
            "id": "T10",
            "type": "Gene",
            "name": "insulin",
            "Name": "insulin"
        },
        {
            "id": "T13",
            "type": "Gene",
            "name": "hCG",
            "Name": "hcg"
        },
        {
            "id": "T2",
            "type": "Gene",
            "name": "P450scc",
            "Name": "p450scc"
        },
        {
            "id": "T3",
            "type": "Gene",
            "name": "CYP17",
            "Name": "cyp17"
        },
        {
            "id": "T4",
            "type": "Gene",
            "name": "insulin",
            "Name": "insulin"
        },
        {
            "id": "T5",
            "type": "Gene",
            "name": "hCG",
            "Name": "hcg"
        },
        {
            "id": "T1",
            "type": "Chemical",
            "name": "androgen",
            "Name": "androgen"
        },
        {
            "id": "T6",
            "type": "Gene",
            "name": "insulin",
            "Name": "insulin"
        },
        {
            "id": "T7",
            "type": "Gene",
            "name": "hCG",
            "Name": "hcg"
        },
        {
            "id": "T8",
            "type": "Gene",
            "name": "P450scc",
            "Name": "p450scc"
        },
        {
            "id": "T9",
            "type": "Gene",
            "name": "CYP17",
            "Name": "cyp17"
        },
        {
            "id": "T11",
            "type": "Gene",
            "name": "insulin",
            "Name": "insulin"
        },
        {
            "id": "T12",
            "type": "Gene",
            "name": "hCG",
            "Name": "hcg"
        }
    ],
    "equivalences": [],
    "relationships": []
}