{
    "entities": [
        {
            "id": "T3",
            "type": "Chemical",
            "name": "TiO2",
            "Name": "tio2"
        },
        {
            "id": "T2",
            "type": "Chemical",
            "name": "TiO2",
            "Name": "tio2"
        },
        {
            "id": "T4",
            "type": "Gene",
            "name": "fibronectin",
            "Name": "fibronectin"
        },
        {
            "id": "T5",
            "type": "Gene",
            "name": "vitronectin",
            "Name": "vitronectin"
        },
        {
            "id": "T1",
            "type": "Chemical",
            "name": "TiO2",
            "Name": "tio2"
        }
    ],
    "equivalences": [],
    "relationships": []
}