{
    "entities": [
        {
            "id": "T43",
            "type": "Gene",
            "name": "CYP2E1",
            "Name": "cyp2e1"
        },
        {
            "id": "T44",
            "type": "Gene",
            "name": "CYP2B4",
            "Name": "cyp2b4"
        },
        {
            "id": "T6",
            "type": "Chemical",
            "name": "NADPH",
            "Name": "nadph"
        },
        {
            "id": "T45",
            "type": "Gene",
            "name": "NADPH-cytochrome P450 reductase",
            "Name": "nadphcytochromep450reductase"
        },
        {
            "id": "T39",
            "type": "Gene",
            "name": "cytochrome P450",
            "Name": "cytochromep450"
        },
        {
            "id": "T26",
            "type": "Gene",
            "name": "CYP2E1",
            "Name": "cyp2e1"
        },
        {
            "id": "T27",
            "type": "Gene",
            "name": "CYP2B4",
            "Name": "cyp2b4"
        },
        {
            "id": "T28",
            "type": "Gene",
            "name": "CYP2E1",
            "Name": "cyp2e1"
        },
        {
            "id": "T29",
            "type": "Gene",
            "name": "CYP2B4",
            "Name": "cyp2b4"
        },
        {
            "id": "T2",
            "type": "Chemical",
            "name": "benzphetamine",
            "Name": "benzphetamine"
        },
        {
            "id": "T3",
            "type": "Chemical",
            "name": "BNZ",
            "Name": "bnz"
        },
        {
            "id": "T30",
            "type": "Gene",
            "name": "CYP2B4",
            "Name": "cyp2b4"
        },
        {
            "id": "T31",
            "type": "Gene",
            "name": "CYP2E1",
            "Name": "cyp2e1"
        },
        {
            "id": "T4",
            "type": "Chemical",
            "name": "p-nitrophenol",
            "Name": "pnitrophenol"
        },
        {
            "id": "T5",
            "type": "Chemical",
            "name": "tert-butyl hydroperoxide",
            "Name": "tertbutylhydroperoxide"
        },
        {
            "id": "T32",
            "type": "Gene",
            "name": "CYP2E1",
            "Name": "cyp2e1"
        },
        {
            "id": "T33",
            "type": "Gene",
            "name": "CYP2B4",
            "Name": "cyp2b4"
        },
        {
            "id": "T34",
            "type": "Gene",
            "name": "CYP2B4",
            "Name": "cyp2b4"
        },
        {
            "id": "T35",
            "type": "Gene",
            "name": "CPR",
            "Name": "cpr"
        },
        {
            "id": "T36",
            "type": "Gene",
            "name": "CYP2E1",
            "Name": "cyp2e1"
        },
        {
            "id": "T37",
            "type": "Gene",
            "name": "CYP2B4",
            "Name": "cyp2b4"
        },
        {
            "id": "T38",
            "type": "Gene",
            "name": "CYP2E1",
            "Name": "cyp2e1"
        },
        {
            "id": "T40",
            "type": "Gene",
            "name": "CYP2E1",
            "Name": "cyp2e1"
        },
        {
            "id": "T41",
            "type": "Gene",
            "name": "CYP2B4",
            "Name": "cyp2b4"
        },
        {
            "id": "T42",
            "type": "Gene",
            "name": "CPR",
            "Name": "cpr"
        },
        {
            "id": "T7",
            "type": "Gene",
            "name": "CYP2E",
            "Name": "cyp2e"
        },
        {
            "id": "T8",
            "type": "Gene",
            "name": "CYP2B4",
            "Name": "cyp2b4"
        },
        {
            "id": "T9",
            "type": "Gene",
            "name": "CPR",
            "Name": "cpr"
        },
        {
            "id": "T10",
            "type": "Gene",
            "name": "CYP2E1",
            "Name": "cyp2e1"
        },
        {
            "id": "T11",
            "type": "Gene",
            "name": "CYP2E1",
            "Name": "cyp2e1"
        },
        {
            "id": "T12",
            "type": "Gene",
            "name": "CYP2B4",
            "Name": "cyp2b4"
        },
        {
            "id": "T1",
            "type": "Chemical",
            "name": "BNZ",
            "Name": "bnz"
        },
        {
            "id": "T13",
            "type": "Gene",
            "name": "CPR",
            "Name": "cpr"
        },
        {
            "id": "T14",
            "type": "Gene",
            "name": "CYP2B4",
            "Name": "cyp2b4"
        },
        {
            "id": "T15",
            "type": "Gene",
            "name": "CYP2E1",
            "Name": "cyp2e1"
        },
        {
            "id": "T16",
            "type": "Gene",
            "name": "CPR",
            "Name": "cpr"
        },
        {
            "id": "T17",
            "type": "Gene",
            "name": "CYP2E1",
            "Name": "cyp2e1"
        },
        {
            "id": "T18",
            "type": "Gene",
            "name": "CPR",
            "Name": "cpr"
        },
        {
            "id": "T19",
            "type": "Gene",
            "name": "CYP2B4",
            "Name": "cyp2b4"
        },
        {
            "id": "T20",
            "type": "Gene",
            "name": "CYP2B4",
            "Name": "cyp2b4"
        },
        {
            "id": "T21",
            "type": "Gene",
            "name": "CYP2E1",
            "Name": "cyp2e1"
        },
        {
            "id": "T22",
            "type": "Gene",
            "name": "CPR",
            "Name": "cpr"
        },
        {
            "id": "T23",
            "type": "Gene",
            "name": "CYP2E1",
            "Name": "cyp2e1"
        },
        {
            "id": "T24",
            "type": "Gene",
            "name": "CYP2B4",
            "Name": "cyp2b4"
        },
        {
            "id": "T25",
            "type": "Gene",
            "name": "CPR",
            "Name": "cpr"
        }
    ],
    "equivalences": [],
    "relationships": [
        {
            "type": "Substrate",
            "source": "T2",
            "target": "T29"
        },
        {
            "type": "Substrate",
            "source": "T3",
            "target": "T29"
        },
        {
            "type": "Substrate",
            "source": "T4",
            "target": "T31"
        },
        {
            "type": "Direct regulator",
            "source": "T1",
            "target": "T12"
        }
    ]
}