{
    "entities": [
        {
            "id": "T1",
            "type": "Chemical",
            "name": "metal-oxide",
            "Name": "metaloxide"
        },
        {
            "id": "T2",
            "type": "Chemical",
            "name": "alkyne",
            "Name": "alkyne"
        },
        {
            "id": "T3",
            "type": "Chemical",
            "name": "azide",
            "Name": "azide"
        },
        {
            "id": "T4",
            "type": "Chemical",
            "name": "indocyanine green",
            "Name": "indocyaninegreen"
        },
        {
            "id": "T6",
            "type": "Gene",
            "name": "bovine serum albumin",
            "Name": "bovineserumalbumin"
        },
        {
            "id": "T5",
            "type": "Chemical",
            "name": "indocyanine green",
            "Name": "indocyaninegreen"
        }
    ],
    "equivalences": [],
    "relationships": []
}