{
    "entities": [
        {
            "id": "T18",
            "type": "Chemical",
            "name": "Alkyl substituted 2'-benzoylpyridine thiosemicarbazone",
            "Name": "alkylsubstituted2benzoylpyridinethiosemicarbazone"
        },
        {
            "id": "T20",
            "type": "Gene",
            "name": "methemoglobin",
            "Name": "methemoglobin"
        },
        {
            "id": "T1",
            "type": "Chemical",
            "name": "Thiosemicarbazone",
            "Name": "thiosemicarbazone"
        },
        {
            "id": "T9",
            "type": "Chemical",
            "name": "2'-benzoylpyridine thiosemicarbazones",
            "Name": "2benzoylpyridinethiosemicarbazones"
        },
        {
            "id": "T15",
            "type": "Chemical",
            "name": "BpT",
            "Name": "bpt"
        },
        {
            "id": "T5",
            "type": "Chemical",
            "name": "3-aminopyridine-2-carboxaldehyde thiosemicarbazone",
            "Name": "3aminopyridine2carboxaldehydethiosemicarbazone"
        },
        {
            "id": "T6",
            "type": "Chemical",
            "name": "3-AP",
            "Name": "3ap"
        },
        {
            "id": "T7",
            "type": "Chemical",
            "name": "3-AP",
            "Name": "3ap"
        },
        {
            "id": "T8",
            "type": "Chemical",
            "name": "BpT",
            "Name": "bpt"
        },
        {
            "id": "T10",
            "type": "Chemical",
            "name": "phenyl",
            "Name": "phenyl"
        },
        {
            "id": "T11",
            "type": "Chemical",
            "name": "RBpT",
            "Name": "rbpt"
        },
        {
            "id": "T12",
            "type": "Chemical",
            "name": "Fe(III/II)",
            "Name": "feiiiii"
        },
        {
            "id": "T13",
            "type": "Chemical",
            "name": "RBpT",
            "Name": "rbpt"
        },
        {
            "id": "T14",
            "type": "Chemical",
            "name": "BpT",
            "Name": "bpt"
        },
        {
            "id": "T19",
            "type": "Gene",
            "name": "methemoglobin",
            "Name": "methemoglobin"
        },
        {
            "id": "T16",
            "type": "Chemical",
            "name": "t-BuBpT",
            "Name": "tbubpt"
        },
        {
            "id": "T17",
            "type": "Chemical",
            "name": "3-AP",
            "Name": "3ap"
        },
        {
            "id": "T2",
            "type": "Chemical",
            "name": "t-BuBpT",
            "Name": "tbubpt"
        },
        {
            "id": "T3",
            "type": "Chemical",
            "name": "3-AP",
            "Name": "3ap"
        },
        {
            "id": "T4",
            "type": "Chemical",
            "name": "thiosemicarbazones",
            "Name": "thiosemicarbazones"
        }
    ],
    "equivalences": [],
    "relationships": [
        {
            "type": "Direct regulator",
            "source": "T18",
            "target": "T20"
        },
        {
            "type": "Indirect downregulator",
            "source": "T16",
            "target": "T19"
        },
        {
            "type": "Indirect downregulator",
            "source": "T17",
            "target": "T19"
        }
    ]
}