{
    "entities": [
        {
            "id": "T50",
            "type": "Gene",
            "name": "Anterior gradient 2 and 3",
            "Name": "anteriorgradient2and3"
        },
        {
            "id": "T26",
            "type": "Chemical",
            "name": "androgen",
            "Name": "androgen"
        },
        {
            "id": "T24",
            "type": "Chemical",
            "name": "androgens",
            "Name": "androgens"
        },
        {
            "id": "T25",
            "type": "Chemical",
            "name": "oestrogens",
            "Name": "oestrogens"
        },
        {
            "id": "T1",
            "type": "Chemical",
            "name": "Androgens",
            "Name": "androgens"
        },
        {
            "id": "T11",
            "type": "Chemical",
            "name": "oestrogens",
            "Name": "oestrogens"
        },
        {
            "id": "T8",
            "type": "Chemical",
            "name": "androgens",
            "Name": "androgens"
        },
        {
            "id": "T16",
            "type": "Chemical",
            "name": "oestrogen",
            "Name": "oestrogen"
        },
        {
            "id": "T17",
            "type": "Chemical",
            "name": "androgens",
            "Name": "androgens"
        },
        {
            "id": "T18",
            "type": "Chemical",
            "name": "oestrogens",
            "Name": "oestrogens"
        },
        {
            "id": "T39",
            "type": "Gene",
            "name": "anterior gradient 2",
            "Name": "anteriorgradient2"
        },
        {
            "id": "T40",
            "type": "Gene",
            "name": "AGR2",
            "Name": "agr2"
        },
        {
            "id": "T41",
            "type": "Gene",
            "name": "anterior gradient 3",
            "Name": "anteriorgradient3"
        },
        {
            "id": "T42",
            "type": "Gene",
            "name": "AGR3",
            "Name": "agr3"
        },
        {
            "id": "T43",
            "type": "Gene",
            "name": "AGR2",
            "Name": "agr2"
        },
        {
            "id": "T19",
            "type": "Chemical",
            "name": "androgen",
            "Name": "androgen"
        },
        {
            "id": "T44",
            "type": "Gene",
            "name": "AGR2",
            "Name": "agr2"
        },
        {
            "id": "T45",
            "type": "Gene",
            "name": "AGR3",
            "Name": "agr3"
        },
        {
            "id": "T20",
            "type": "Chemical",
            "name": "androgen",
            "Name": "androgen"
        },
        {
            "id": "T46",
            "type": "Gene",
            "name": "androgen receptor",
            "Name": "androgenreceptor"
        },
        {
            "id": "T47",
            "type": "Gene",
            "name": "AGR",
            "Name": "agr"
        },
        {
            "id": "T21",
            "type": "Chemical",
            "name": "oestradiol",
            "Name": "oestradiol"
        },
        {
            "id": "T22",
            "type": "Chemical",
            "name": "oestrogen",
            "Name": "oestrogen"
        },
        {
            "id": "T48",
            "type": "Gene",
            "name": "oestrogen receptor",
            "Name": "oestrogenreceptor"
        },
        {
            "id": "T23",
            "type": "Chemical",
            "name": "androgen",
            "Name": "androgen"
        },
        {
            "id": "T49",
            "type": "Gene",
            "name": "androgen receptor",
            "Name": "androgenreceptor"
        },
        {
            "id": "T2",
            "type": "Chemical",
            "name": "androgen",
            "Name": "androgen"
        },
        {
            "id": "T27",
            "type": "Gene",
            "name": "androgen receptor",
            "Name": "androgenreceptor"
        },
        {
            "id": "T3",
            "type": "Chemical",
            "name": "oestrogen",
            "Name": "oestrogen"
        },
        {
            "id": "T28",
            "type": "Gene",
            "name": "oestrogen receptor",
            "Name": "oestrogenreceptor"
        },
        {
            "id": "T4",
            "type": "Chemical",
            "name": "androgen",
            "Name": "androgen"
        },
        {
            "id": "T5",
            "type": "Chemical",
            "name": "oestrogen",
            "Name": "oestrogen"
        },
        {
            "id": "T6",
            "type": "Chemical",
            "name": "androgen",
            "Name": "androgen"
        },
        {
            "id": "T7",
            "type": "Chemical",
            "name": "oestrogen",
            "Name": "oestrogen"
        },
        {
            "id": "T29",
            "type": "Gene",
            "name": "FKBP5",
            "Name": "fkbp5"
        },
        {
            "id": "T9",
            "type": "Chemical",
            "name": "androgen",
            "Name": "androgen"
        },
        {
            "id": "T10",
            "type": "Chemical",
            "name": "androgen",
            "Name": "androgen"
        },
        {
            "id": "T30",
            "type": "Gene",
            "name": "androgen receptor",
            "Name": "androgenreceptor"
        },
        {
            "id": "T31",
            "type": "Gene",
            "name": "AGR2",
            "Name": "agr2"
        },
        {
            "id": "T32",
            "type": "Gene",
            "name": "AGR3",
            "Name": "agr3"
        },
        {
            "id": "T12",
            "type": "Chemical",
            "name": "androgen",
            "Name": "androgen"
        },
        {
            "id": "T13",
            "type": "Chemical",
            "name": "Androgen",
            "Name": "androgen"
        },
        {
            "id": "T33",
            "type": "Gene",
            "name": "p300",
            "Name": "p300"
        },
        {
            "id": "T34",
            "type": "Gene",
            "name": "RNA Pol II",
            "Name": "rnapolii"
        },
        {
            "id": "T14",
            "type": "Chemical",
            "name": "androgen",
            "Name": "androgen"
        },
        {
            "id": "T35",
            "type": "Gene",
            "name": "androgen receptor",
            "Name": "androgenreceptor"
        },
        {
            "id": "T36",
            "type": "Gene",
            "name": "AGR2",
            "Name": "agr2"
        },
        {
            "id": "T37",
            "type": "Gene",
            "name": "RNA Pol II",
            "Name": "rnapolii"
        },
        {
            "id": "T15",
            "type": "Chemical",
            "name": "androgen",
            "Name": "androgen"
        },
        {
            "id": "T38",
            "type": "Gene",
            "name": "androgen receptor",
            "Name": "androgenreceptor"
        }
    ],
    "equivalences": [],
    "relationships": [
        {
            "type": "Indirect downregulator",
            "source": "T21",
            "target": "T47"
        },
        {
            "type": "Indirect downregulator",
            "source": "T19",
            "target": "T44"
        },
        {
            "type": "Indirect downregulator",
            "source": "T19",
            "target": "T45"
        },
        {
            "type": "Indirect downregulator",
            "source": "T19",
            "target": "T46"
        },
        {
            "type": "Indirect downregulator",
            "source": "T13",
            "target": "T33"
        },
        {
            "type": "Indirect downregulator",
            "source": "T13",
            "target": "T34"
        },
        {
            "type": "Indirect downregulator",
            "source": "T13",
            "target": "T37"
        },
        {
            "type": "Activator",
            "source": "T13",
            "target": "T38"
        }
    ]
}