{
    "entities": [
        {
            "id": "T6",
            "type": "Chemical",
            "name": "thiopurine",
            "Name": "thiopurine"
        },
        {
            "id": "T3",
            "type": "Chemical",
            "name": "thiopurine",
            "Name": "thiopurine"
        },
        {
            "id": "T4",
            "type": "Chemical",
            "name": "thiopurine",
            "Name": "thiopurine"
        },
        {
            "id": "T5",
            "type": "Chemical",
            "name": "thiopurine",
            "Name": "thiopurine"
        },
        {
            "id": "T14",
            "type": "Gene",
            "name": "TPMT",
            "Name": "tpmt"
        },
        {
            "id": "T7",
            "type": "Gene",
            "name": "IL6ST",
            "Name": "il6st"
        },
        {
            "id": "T8",
            "type": "Gene",
            "name": "cytokines",
            "Name": "cytokines"
        },
        {
            "id": "T9",
            "type": "Gene",
            "name": "IL6",
            "Name": "il6"
        },
        {
            "id": "T10",
            "type": "Gene",
            "name": "FSTL5",
            "Name": "fstl5"
        },
        {
            "id": "T11",
            "type": "Gene",
            "name": "metalloproteases",
            "Name": "metalloproteases"
        },
        {
            "id": "T12",
            "type": "Gene",
            "name": "IL6ST",
            "Name": "il6st"
        },
        {
            "id": "T13",
            "type": "Gene",
            "name": "FSLT5",
            "Name": "fslt5"
        },
        {
            "id": "T1",
            "type": "Chemical",
            "name": "thiopurine",
            "Name": "thiopurine"
        },
        {
            "id": "T2",
            "type": "Chemical",
            "name": "thiopurine",
            "Name": "thiopurine"
        }
    ],
    "equivalences": [],
    "relationships": []
}