{
    "entities": [
        {
            "id": "T24",
            "type": "Gene",
            "name": "angiopoietin-1",
            "Name": "angiopoietin1"
        },
        {
            "id": "T10",
            "type": "Chemical",
            "name": "phosgene",
            "Name": "phosgene"
        },
        {
            "id": "T5",
            "type": "Chemical",
            "name": "phosgene",
            "Name": "phosgene"
        },
        {
            "id": "T11",
            "type": "Gene",
            "name": "Angiopoietin-1",
            "Name": "angiopoietin1"
        },
        {
            "id": "T16",
            "type": "Gene",
            "name": "Ang1",
            "Name": "ang1"
        },
        {
            "id": "T6",
            "type": "Chemical",
            "name": "phosgene",
            "Name": "phosgene"
        },
        {
            "id": "T20",
            "type": "Gene",
            "name": "Ang1",
            "Name": "ang1"
        },
        {
            "id": "T7",
            "type": "Chemical",
            "name": "phosgene",
            "Name": "phosgene"
        },
        {
            "id": "T21",
            "type": "Gene",
            "name": "Ang1",
            "Name": "ang1"
        },
        {
            "id": "T22",
            "type": "Gene",
            "name": "Ang1",
            "Name": "ang1"
        },
        {
            "id": "T8",
            "type": "Chemical",
            "name": "Haematoxylin",
            "Name": "haematoxylin"
        },
        {
            "id": "T9",
            "type": "Chemical",
            "name": "Eosin",
            "Name": "eosin"
        },
        {
            "id": "T23",
            "type": "Gene",
            "name": "cytokines",
            "Name": "cytokines"
        },
        {
            "id": "T1",
            "type": "Chemical",
            "name": "phosgene",
            "Name": "phosgene"
        },
        {
            "id": "T12",
            "type": "Gene",
            "name": "Ang1",
            "Name": "ang1"
        },
        {
            "id": "T13",
            "type": "Gene",
            "name": "IL-1\u03b2",
            "Name": "il1\u03b2"
        },
        {
            "id": "T14",
            "type": "Gene",
            "name": "IL-17",
            "Name": "il17"
        },
        {
            "id": "T15",
            "type": "Gene",
            "name": "vascular endothelial growth factor",
            "Name": "vascularendothelialgrowthfactor"
        },
        {
            "id": "T2",
            "type": "Chemical",
            "name": "phosgene",
            "Name": "phosgene"
        },
        {
            "id": "T17",
            "type": "Gene",
            "name": "Ang1",
            "Name": "ang1"
        },
        {
            "id": "T18",
            "type": "Gene",
            "name": "Ang1",
            "Name": "ang1"
        },
        {
            "id": "T3",
            "type": "Chemical",
            "name": "phosgene",
            "Name": "phosgene"
        },
        {
            "id": "T19",
            "type": "Gene",
            "name": "Ang1",
            "Name": "ang1"
        },
        {
            "id": "T4",
            "type": "Chemical",
            "name": "phosgene",
            "Name": "phosgene"
        }
    ],
    "equivalences": [],
    "relationships": []
}