{
    "entities": [
        {
            "id": "T11",
            "type": "Plant",
            "name": "Cavendish bananas",
            "NCBI_Taxonomy": "214697"
        },
        {
            "id": "T12",
            "type": "Pest",
            "name": "TR4 fungus",
            "NCBI_Taxonomy": "2502994"
        },
        {
            "id": "T13",
            "type": "Location",
            "name": "Colombia",
            "GeoNames": "3686110"
        },
        {
            "id": "T14",
            "type": "Plant",
            "name": "Cavendish bananas",
            "NCBI_Taxonomy": "214697"
        },
        {
            "id": "T15",
            "type": "Pest",
            "name": "TR4 fungus",
            "NCBI_Taxonomy": "2502994"
        },
        {
            "id": "T16",
            "type": "Plant",
            "name": "Cavendish banana plants",
            "NCBI_Taxonomy": "214697"
        },
        {
            "id": "T17",
            "type": "Pest",
            "name": "TR4",
            "NCBI_Taxonomy": "2502994"
        },
        {
            "id": "T19",
            "type": "Plant",
            "name": "bananas",
            "NCBI_Taxonomy": "4640"
        },
        {
            "id": "T20",
            "type": "Plant",
            "name": "Gros Michel variety",
            "NCBI_Taxonomy": "214697"
        },
        {
            "id": "T21",
            "type": "Pest",
            "name": "TR1",
            "NCBI_Taxonomy": "1229664"
        },
        {
            "id": "T22",
            "type": "Plant",
            "name": "banana crops",
            "NCBI_Taxonomy": "4640"
        },
        {
            "id": "T23",
            "type": "Plant",
            "name": "variety of banana called Cavendish",
            "NCBI_Taxonomy": "214697"
        },
        {
            "id": "T24",
            "type": "Pest",
            "name": "TR1 fungus",
            "NCBI_Taxonomy": "1229664"
        },
        {
            "id": "T25",
            "type": "Pest",
            "name": "TR4",
            "NCBI_Taxonomy": "2502994"
        },
        {
            "id": "T26",
            "type": "Plant",
            "name": "Cavendish bananas",
            "NCBI_Taxonomy": "214697"
        },
        {
            "id": "T28",
            "type": "Plant",
            "name": "Cavendish plants",
            "NCBI_Taxonomy": "214697"
        },
        {
            "id": "T29",
            "type": "Pest",
            "name": "TR4",
            "NCBI_Taxonomy": "2502994"
        },
        {
            "id": "T30",
            "type": "Plant",
            "name": "Cavendish",
            "NCBI_Taxonomy": "214697"
        },
        {
            "id": "T31",
            "type": "Pest",
            "name": "TR1",
            "NCBI_Taxonomy": "1229664"
        },
        {
            "id": "T32",
            "type": "Pest",
            "name": "TR4",
            "NCBI_Taxonomy": "2502994"
        },
        {
            "id": "T33",
            "type": "Pest",
            "name": "TR1 fungus",
            "NCBI_Taxonomy": "1229664"
        },
        {
            "id": "T34",
            "type": "Pest",
            "name": "TR4",
            "NCBI_Taxonomy": "2502994"
        },
        {
            "id": "T35",
            "type": "Pest",
            "name": "TR1",
            "NCBI_Taxonomy": "1229664"
        },
        {
            "id": "T36",
            "type": "Pest",
            "name": "TR4",
            "NCBI_Taxonomy": "2502994"
        },
        {
            "id": "T38",
            "type": "Pest",
            "name": "TR4",
            "NCBI_Taxonomy": "2502994"
        },
        {
            "id": "T39",
            "type": "Plant",
            "name": "banana",
            "NCBI_Taxonomy": "4640"
        },
        {
            "id": "T40",
            "type": "Disease",
            "name": "Fusarium wilt"
        },
        {
            "id": "T41",
            "type": "Pest",
            "name": "Tropical Race 4",
            "NCBI_Taxonomy": "2502994"
        },
        {
            "id": "T42",
            "type": "Plant",
            "name": "Cavendish cv Grand Naine bananas",
            "NCBI_Taxonomy": "214697"
        }
    ],
    "equivalences": [
        [
            "T32",
            "T34"
        ],
        [
            "T31",
            "T33"
        ]
    ],
    "relationships": [
        {
            "type": "Has been found on",
            "source": "T12",
            "target": "T11"
        },
        {
            "type": "Has been found on",
            "source": "T15",
            "target": "T14"
        },
        {
            "type": "Has been found on",
            "source": "T17",
            "target": "T16"
        },
        {
            "type": "Has been found on",
            "source": "T21",
            "target": "T22"
        },
        {
            "type": "Has been found on",
            "source": "T24",
            "target": "T23"
        },
        {
            "type": "Has been found on",
            "source": "T25",
            "target": "T26"
        },
        {
            "type": "Has been found on",
            "source": "T29",
            "target": "T28"
        },
        {
            "type": "Has been found on",
            "source": "T31",
            "target": "T30"
        },
        {
            "type": "Has been found on",
            "source": "T32",
            "target": "T30"
        },
        {
            "type": "Causes",
            "source": "T41",
            "target": "T40"
        },
        {
            "type": "Affects",
            "source": "T40",
            "target": "T39"
        },
        {
            "type": "Affects",
            "source": "T40",
            "target": "T42"
        },
        {
            "type": "Has been found on",
            "source": "T41",
            "target": "T39"
        },
        {
            "type": "Has been found on",
            "source": "T41",
            "target": "T42"
        }
    ]
}